skrewmpcpy/__init__.py
skrewmpcpy/_version.py
skrewmpcpy/_version.pyi
skrewmpcpy/basemg.py
skrewmpcpy/pandamg.py
skrewmpcpy/py.typed
skrewmpcpy/skrewmpc.py
skrewmpcpy/util.py
skrewmpcpy-0.1.1.dist-info/METADATA
skrewmpcpy-0.1.1.dist-info/WHEEL
skrewmpcpy-0.1.1.dist-info/licenses/LICENSE
skrewmpcpy-0.1.1.dist-info/RECORD
