Metadata-Version: 2.1
Name: skrewmpcpy
Version: 0.1.1
Summary: Dual Quaternion based MPC generating skrew motion for n-DOF robot arm.
Project-URL: Homepage, https://github.com/greinerth/skrewmpcpy
Project-URL: Bug Tracker, https://github.com/greinerth/skrewmpcpy/issues
Project-URL: Discussions, https://github.com/greinerth/skrewmpcpy/discussions
Project-URL: Changelog, https://github.com/greinerth/skrewmpcpy/releases
Author-email: Gerhard Reinerth <g.reinerth@tum.de>
License: Copyright 2024 Gerhard Reinerth
License-File: LICENSE
Classifier: Development Status :: 1 - Planning
Classifier: Intended Audience :: Developers
Classifier: Intended Audience :: Science/Research
Classifier: License :: OSI Approved :: MIT License
Classifier: Operating System :: OS Independent
Classifier: Programming Language :: Python
Classifier: Programming Language :: Python :: 3
Classifier: Programming Language :: Python :: 3 :: Only
Classifier: Programming Language :: Python :: 3.8
Classifier: Programming Language :: Python :: 3.9
Classifier: Programming Language :: Python :: 3.10
Classifier: Programming Language :: Python :: 3.11
Classifier: Topic :: Scientific/Engineering
Classifier: Typing :: Typed
Requires-Python: <3.12,>=3.8
Requires-Dist: dqrobotics==23.4.0a22
Requires-Dist: nptyping
Requires-Dist: numpy>=1.24.0
Requires-Dist: osqp
Requires-Dist: scipy>=1.10.0
Provides-Extra: dev
Requires-Dist: bumpver; extra == 'dev'
Requires-Dist: furo>=2023.08.17; extra == 'dev'
Requires-Dist: myst-parser>=0.13; extra == 'dev'
Requires-Dist: nox; extra == 'dev'
Requires-Dist: pre-commit; extra == 'dev'
Requires-Dist: pytest-cov>=3; extra == 'dev'
Requires-Dist: pytest-mypy; extra == 'dev'
Requires-Dist: pytest>=6; extra == 'dev'
Requires-Dist: ruff; extra == 'dev'
Requires-Dist: sphinx-autodoc-typehints; extra == 'dev'
Requires-Dist: sphinx-copybutton; extra == 'dev'
Requires-Dist: sphinx>=7.0; extra == 'dev'
Requires-Dist: twine; extra == 'dev'
Provides-Extra: docs
Requires-Dist: furo>=2023.08.17; extra == 'docs'
Requires-Dist: myst-parser>=0.13; extra == 'docs'
Requires-Dist: sphinx-autodoc-typehints; extra == 'docs'
Requires-Dist: sphinx-copybutton; extra == 'docs'
Requires-Dist: sphinx>=7.0; extra == 'docs'
Provides-Extra: test
Requires-Dist: nox; extra == 'test'
Requires-Dist: pytest-cov>=3; extra == 'test'
Requires-Dist: pytest-mypy; extra == 'test'
Requires-Dist: pytest>=6; extra == 'test'
Requires-Dist: ruff; extra == 'test'
